factom/__init__.py
factom/client.py
factom/exceptions.py
factom/session.py
factom/utils.py
tests/integration/__init__.py
tests/integration/test_api.py
factom_api-1.0.2.dist-info/LICENSE
factom_api-1.0.2.dist-info/METADATA
factom_api-1.0.2.dist-info/WHEEL
factom_api-1.0.2.dist-info/top_level.txt
factom_api-1.0.2.dist-info/RECORD
